mynameiswanwa
