Metadata-Version: 1.1
Name: mynameiswanwa
Version: 0.0.3
Summary: Who is Wanwa?
Home-page: https://github.com/pinateP/
Author: Wanwa Poonsawat
Author-email: wanwa.p@gmail.com
License: MIT
Download-URL: https://github.com/pinateP/mynameiswanwa
Keywords: mynameiswanwa,pinateP
Platform: UNKNOWN
Classifier: Development Status :: 3 - Alpha
Classifier: Intended Audience :: Education
Classifier: Topic :: Utilities
Classifier: License :: OSI Approved :: MIT License
Classifier: Programming Language :: Python :: 3
Classifier: Programming Language :: Python :: 3.4
Classifier: Programming Language :: Python :: 3.5
Classifier: Programming Language :: Python :: 3.6
Classifier: Programming Language :: Python :: 3.7
Classifier: Programming Language :: Python :: 3.8
Classifier: Programming Language :: Python :: 3.9
Classifier: Programming Language :: Python :: 3.10
